znjson/__init__.py
znjson/base.py
znjson/config.py
znjson/converter/__init__.py
znjson/converter/class_converter.py
znjson/converter/numpy_converter_base64.py
znjson/converter/numpy_converter_small.py
znjson/converter/old_converters.py
znjson/converter/pathlib_converter.py
znjson/converter/plotly_converter.py
znjson/exceptions/__init__.py
znjson/main.py
znjson-0.2.6.dist-info/LICENSE
znjson-0.2.6.dist-info/METADATA
znjson-0.2.6.dist-info/WHEEL
znjson-0.2.6.dist-info/RECORD
