Metadata-Version: 2.1
Name: znjson
Version: 0.2.6
Summary: A Python Package to Encode/Decode some common file formats to json
License: Apache-2.0
Keywords: json,zntrack,jsonpickle,serialization,deserialization
Author: zincwarecode
Author-email: zincwarecode@gmail.com
Requires-Python: >=3.9,<4.0
Classifier: License :: OSI Approved :: Apache Software License
Classifier: Programming Language :: Python :: 3
Classifier: Programming Language :: Python :: 3.9
Classifier: Programming Language :: Python :: 3.10
Classifier: Programming Language :: Python :: 3.11
Classifier: Programming Language :: Python :: 3.12
Project-URL: repository, https://github.com/zincware/ZnJSON
